<?xml version="1.0"?>
<?xml-stylesheet type="text/css" href="c:\inetpub\webpubdotnet\directio\web\css\bases\fipbinvkhs.css" ?>
<top>
    <TIT4/>
    <INVID ID="FRB.FOBJ2.SCAL.2019">FRB.FOBJ2.SCAL.2019</INVID>
    <P>
        <AI R="FOBJSCAL/FOBJSCAL2019AR.jpg$$">
            <IMG SRC="$RELDIR$FOBJSCAL/FOBJSCAL2019AR_v.jpg"/>
        </AI>
        <AI R="FOBJSCAL/FOBJSCAL2019BR.jpg$$">
            <IMG SRC="$RELDIR$FOBJSCAL/FOBJSCAL2019BR_v.jpg"/>
        </AI>
        <AI R="FOBJSCAL/FOBJSCAL2019CR.jpg$$">
            <IMG SRC="$RELDIR$FOBJSCAL/FOBJSCAL2019CR_v.jpg"/>
        </AI>
        <AI R="FOBJSCAL/FOBJSCAL2019DR.jpg$$">
            <IMG SRC="$RELDIR$FOBJSCAL/FOBJSCAL2019DR_v.jpg"/>
        </AI>
    </P>
    <ISBD>
        <Z1>
            <TITI>
                <NXP LNP="Monroe">Monroe LA7-160</NXP>
                <T>: machine &#x00e0; calculer m&#x00e9;canique</T>
            </TITI>
        </Z1>
        <Z0>
            <TYPE>Objet : sans m&#x00e9;diation</TYPE>
            <INV>2014</INV>
            <LIEU>C8-H1.5</LIEU>
        </Z0>
        <Z2>
            <SXP>Model LA7-160</SXP>
            <T></T>
            <SXP>S/N B-106623</SXP>
        </Z2>
        <Z3/>
        <Z4>
            <NXP>Holland</NXP>
            <T>,</T>
            <NXP>Amsterdam</NXP>
            <T>:</T>
            <NXP>Monroe Calculating Machine Company</NXP>
            <T>,</T>
            <EXP>s.d.</EXP>
        </Z4>
        <Z5>
            <T>L <NB>31</NB> x l <NB>28,5</NB> x H <NB>16,5</NB> cm; <NB>6,8</NB> kg; m&#x00e9;tal et plastic
            </T>
        </Z5>
        <Z6/>
        <Z7>
            <T>Bon &#x00e9;tat</T>
            <B/>
            <T>Plaque:</T>
            <NXP>Monroe</NXP>
            <T></T>
            <NXP>France</NXP>
            <T>, 29 Rue du Fg</T>
            <NXP>St Honor&#x00e9;</NXP>
            <T>-</T>
            <NXP>Paris</NXP>
            <T>(<NB>8&#x00b0;</NB>)
            </T>
            <B/>
            <T>Sce Tech. 103, r de</T>
            <NXP>Tocqueville</NXP>
            <T>(<NB>17&#x00b0;</NB>)
            </T>
        </Z7>
        <Z8>
            <NXP>Collection Jacques Lemaire</NXP>
        </Z8>
    </ISBD>
    <P>
        <DP D="00112019">Date de publication: novembre 2019</DP>
    </P>
</top>
