<?xml version="1.0"?>
<?xml-stylesheet type="text/css" href="c:\inetpub\webpubdotnet\directio\web\css\bases\fipbinvkhs.css" ?>
<top>
<TIT5/> <INVID ID="FRB.AV.VIDEO.1994">FRB.AV.VIDEO.1994 </INVID> <ISBD> <Z1> <TITI> <NXP>FBC</NXP> <T> 25 ans </T> </TITI> </Z1> <Z0> <TYPE/> <INV>2014</INV> <LIEU>HDD/FIPB-DOC-PIC/FNUMPIC</LIEU> </Z0> <Z5/> <Z8> <NXP>Collection I&#x0026;B</NXP> </Z8> </ISBD> <P> <T> </T> <NXP>OCIC-Video</NXP> <T> 25 ans de la </T> <NXP>F&#x00e9;d&#x00e9;ration Biblique Catholique</NXP> <T> 35 min </T> <NXP>RFP</NXP> <T> d&#x00e9;l&#x00e9;gu&#x00e9; de Production, </T> <NXP>RTCB</NXP> </P> <P> <DP D="00112019">Date de publication: novembre 2019</DP> </P>
</top>
