<?xml version="1.0"?>
<?xml-stylesheet type="text/css" href="c:\inetpub\webpubdotnet\directio\web\css\bases\fipbinvkhs.css" ?>
<top>
<TIT4/> <INVID ID="FRB.P.USENT">FRB.P.USENT</INVID> <ISBD> <Z1> <TITI> <T>Usine Entreprise (Magazine du Dirigeant de </T> <NXP>PME</NXP> <T> &#x0026; </T> <NXP>PMI</NXP> <T>)</T> </TITI> </Z1> <Z0> <TYPE>Texte: sans m&#x00e9;diation</TYPE> <INV>2014</INV> <LIEU/> </Z0> <Z2/> <Z3/> <Z4/> <Z6> <T/> </Z6> <Z7/> <Z8> <NXP>Collection I&#x0026;B</NXP> </Z8> </ISBD> <P> <DT D="">2008</DT> <T>: N&#x00b0; 3065 &#x2013; 3067 &#x2013; 3068 &#x2013; 3069 &#x2013; 3071 - 3072 - 3073</T> </P> <P> <DT D="">2009</DT> <T>: N&#x00b0; 3075- 3076 - 3077</T> </P> <STIT4> <T>Manquants</T> </STIT4> <P> <DT D="">2008</DT> <T>: N&#x00b0; 3066 </T> </P> <P> <DT D="">2009</DT> <T>: N&#x00b0; 3074 - 3078 - 3079 - 3080 - 3081 -3082 - 3083</T> </P> <P> <DT D="">2010</DT> <T>: N&#x00b0; 3084 - 3085 - 3086 - 3087 - 3088 - 3089 - 3090 - 3091- 3092</T> </P> <P> <DT D="">2011</DT> <T>: N&#x00b0; 3093 - 3094 - 3095 - 3096 - 3097 - 3100 - 3101</T> </P> <P> <DT D="">2012</DT> <T>: N&#x00b0; 3103 - 3104 - 3105 - 3106 - 3107 - 3108 - 3110 - 3111</T> </P> <P><DP D="00112019">Date de publication: novembre 2019</DP></P>
</top>
