<?xml version="1.0"?>
<?xml-stylesheet type="text/css" href="c:\inetpub\webpubdotnet\directio\web\css\bases\fipbinvkhs.css" ?>
<top>
<TIT5/> <INVID ID="FRB.ARCH.IB.PRO-231C">FRB.ARCH.IB.PRO-231C</INVID> <ISBD> <Z1> <TITI> <T> </T> <NXP>H&#x00e9;breu</NXP> <T>: Correction index <NB>II</NB> </T> <DT D="00031981">mars &#x00e0; juin 1981</DT> <T> (Correction lemme, lignes, &#x00e9;l&#x00e9;ments, r&#x00e9;cup&#x00e9;r&#x00e9;s, anomalies) [K 094]</T> </TITI> </Z1> <Z0> <TYPE>Texte: sans m&#x00e9;diation</TYPE> <INV>2014</INV> <LIEU>C3-C1.5 [AR04-IIIF6]</LIEU> </Z0> <Z8> <NXP>Collection I&#x0026;B</NXP> </Z8> </ISBD> <P><DP D="00112019">Date de publication: novembre 2019</DP></P>
</top>
