<?xml version="1.0"?>
<?xml-stylesheet type="text/css" href="c:\inetpub\webpubdotnet\directio\web\css\bases\fipbinvkhs.css" ?>
<top>
<TIT4/> <INVID ID="FRB.BIB.RECH.2110">FRB.BIB.RECH.2110</INVID> <ISBD> <Z1> <TITI><NXP>Goldman</NXP> <T> </T> <NXP>Rohm</NXP> <T> </T> <NXP>Wendy</NXP> <T>. - L'Affaire </T><NXP>Microsoft</NXP><T> : Les charges secr&#x00e8;tes contre </T><NXP>Bill</NXP><T> </T><NXP>Gates</NXP> </TITI> </Z1> <Z0> <TYPE> Texte: sans m&#x00e9;diation</TYPE> <INV>2014</INV> <LIEU>B-B</LIEU> </Z0> <Z2> <T> </T> </Z2> <Z4> <NXP>Paris</NXP> <T> : </T> <NXP>&#x00c9;ditions G&#x00e9;n&#x00e9;rales First</NXP> <T>, </T> <DT D="00001998">1998</DT> </Z4> <Z5> <T>382 p.</T> </Z5> <Z7/> <Z8> <T>ISBN <IS>2-87691-474-3</IS></T> <B/> <NXP>Collection I&#x0026;B</NXP> <T>; Debora 3411</T> </Z8> </ISBD> <P><DP D="00062020">Date de publication: juin 2020</DP></P>
</top>
