<?xml version="1.0"?>
<?xml-stylesheet type="text/css" href="c:\inetpub\webpubdotnet\directio\web\css\bases\fipbinvkhs.css" ?>
<top>
<TIT4/> <INVID ID="FRB.P.ICT">FRB.P.ICT</INVID> <ISBD> <Z1> <TITI> <T/> <NXP>ICT</NXP> <T> Info Support Training Guide Business Information and Communication Technology</T> </TITI> </Z1> <Z0> <TYPE>Texte: sans m&#x00e9;diation</TYPE> <INV>2014</INV> <LIEU/> </Z0> <Z2/> <Z3/> <Z4/> <Z6> <T>Mensuel</T> </Z6> <Z7/> <Z8> <NXP>Collection I&#x0026;B</NXP> </Z8> </ISBD> <P> <DT D="">1998</DT> <T>: N&#x00b0; 596 &#x2013; 598 &#x2013; 600 &#x2013; 602</T> </P> <P> <DT D="">1999</DT> <T>: N&#x00b0; 604 &#x2013; 606 &#x2013; 608 &#x2013; 610 &#x2013; 612 &#x2013; 614 &#x2013; 616 - 618</T> </P> <P> <DT D="">2000</DT> <T>: N&#x00b0; 630 &#x2013; 632 &#x2013; 634 &#x2013; 636 &#x2013; 638 &#x2013; 640 - 642</T> </P> <P> <DT D="">2001</DT> <T>: N&#x00b0; 644 &#x2013; 646 &#x2013; 648 &#x2013; 650 &#x2013; 652 &#x2013; 654 &#x2013; 656 - 658 &#x2013; 660 &#x2013; 662 + Annuaire (Mars)</T> </P> <P> <DT D="">2002</DT> <T>: N&#x00b0; 664 - 666 </T> </P> <STIT4> <T>Manquants</T> </STIT4> <P> <DT D="">1998/2002</DT> <T>Les N&#x00b0; impairs ?</T> </P> <P> <DT D="">2000</DT> <T>: N&#x00b0; 619 29 </T> </P> <P><DP D="00112019">Date de publication: novembre 2019</DP></P>
</top>
