<?xml version="1.0"?>
<?xml-stylesheet type="text/css" href="c:\inetpub\webpubdotnet\directio\web\css\bases\fipbinvkhs.css" ?>
<top>
<TIT4/> <INVID ID="FRB.FOBJ3.SCAL.1136">FRB.FOBJ3.SCAL.1136</INVID> <P> <AI R="FOBJSCAL/FOBJSCAL1136AR.jpg$$"> <IMG SRC="$RELDIR$FOBJSCAL/FOBJSCAL1136AR_v.jpg"/> </AI> <AI R="FOBJSCAL/FOBJSCAL1136BR.jpg$$"> <IMG SRC="$RELDIR$FOBJSCAL/FOBJSCAL1136BR_v.jpg"/> </AI> </P> <ISBD> <Z1> <TITI> <NXP LNP="Hewlett Packard">HP-19B II</NXP> <T> </T> <NXP>Business Consultant II</NXP> <T> : calculatrice financi&#x00e8;re graphique programmable, avec couvercle </T> </TITI> </Z1> <Z0> <TYPE>Objet : </TYPE> <INV>2014</INV> <LIEU>C8-A1.1</LIEU> </Z0> <Z2> <SXP>S/N 93701630</SXP> </Z2> <Z3/> <Z4> <EXP>s.l.</EXP> <T> : </T> <NXP>Hewlett Packard Company</NXP> <T>, </T> <T/> <EXP>s.d.</EXP> </Z4> <Z5> <T>L <NB>18,9</NB> x l <NB>15,9</NB> x H <NB>1,7</NB> cm; <NB>0,1</NB> kg</T> </Z5> <Z6/> <Z7> <T>Bon &#x00e9;tat</T> </Z7> <Z8> <NXP>Collection Jacques Lemaire</NXP> <T> </T> <REF>SYSCAL.68.1136</REF> </Z8> </ISBD> <P> <T>2 claviers: 1 num&#x00e9;rique et 1 alphab&#x00e9;tique</T> </P> <P> <T>made in </T><NXP>Indonesia</NXP><T>, </T> <DT D="00001990">1990</DT> <T>-</T> <DT D="00002001">2001</DT> </P> <P> <T>mode </T><NXP>ALG</NXP><T>, <NB>6,6</NB> kb Ram, 64 kb Rom, 460 fonctions, 78 touches, afficheur 23 x 4 </T><NXP>LCD</NXP><T>, alim. 3 piles N</T> </P> <P><DP D="00112019">Date de publication: novembre 2019</DP></P>
</top>
