<?xml version="1.0"?>
<?xml-stylesheet type="text/css" href="c:\inetpub\webpubdotnet\directio\web\css\bases\fipbinvkhs.css" ?>
<top>
<TIT5/> <INVID ID="FRB.ARCH.IB.EPH-1543B">FRB.ARCH.IB.EPH-1543B</INVID> <ISBD> <Z1> <TITI> <T>Doc</T> <T>: Informatique en cours 2014 - Infos commerciales - Salons - 2 </T> </TITI> </Z1> <Z0> <TYPE>Texte: sans m&#x00e9;diation</TYPE> <INV>2014</INV> <LIEU>A-F3.6 [H13]</LIEU> </Z0> <Z8> <NXP>Collection I&#x0026;B</NXP> </Z8> </ISBD> <P><DP D="00112019">Date de publication: novembre 2019</DP></P>
</top>
